{"cameraMode":{"drawMode":0,"name":"Shaded","section":"Shading Mode"},"sceneLighting":true,"audioPlay":false,"sceneViewState":{"m_AlwaysRefresh":false,"showFog":true,"showSkybox":true,"showFlares":true,"showImageEffects":true,"showParticleSystems":true,"showVisualEffectGraphs":true,"m_FxEnabled":true},"in2DMode":false,"pivot":{"x":-83.92121887207031,"y":-95.4073715209961,"z":119.53643798828125},"rotation":{"x":-0.22669623792171479,"y":0.30939924716949465,"z":-0.07621310651302338,"w":-0.9203875064849854},"size":111.41796875,"orthographic":false}